[
  {
    "VideoId": "d90cb7ed-3112-4faa-bfb8-9dea00a14eb8",
    "DataApi": "/Entries(guid'd90cb7ed-3112-4faa-bfb8-9dea00a14eb8')/",
    "VideoPageLink": "/Blogs/jwiese/Whats-New-SharePoint-2010-Word-Automation-Services-via-Workflow",
    "VideoPageThumb": "https://sec.ch9.ms/ecn/ch9/1/4/9/6/5/5/WhatsNewSPS06WordWF_512_ch9.png",
    "ShowName": "jwiese",
    "VideoLength": "00:21:28",
    "VideoTitle": "What's New: SharePoint 2010 -- Word Automation Services via Workflow",
    "Author": "John Wiese",
    "UtcDateTimePublished": "2010-06-21T20:31:00Z",
    "ActualVideoFileLink": "https://sec.ch9.ms/ecn/ch9/1/4/9/6/5/5/WhatsNewSPS06WordWF_ch9.mp4",
    "Description": "What's New: SharePoint 2010 is a series of screencasts centered on what is new in SharePoint 2010 for developers. My goal is to highlight a majority of the major new features that are of interest to d"
  },
  {
    "VideoId": "d9437287-e1ed-460f-bada-9dea00a15023",
    "DataApi": "/Entries(guid'd9437287-e1ed-460f-bada-9dea00a15023')/",
    "VideoPageLink": "/Blogs/jwiese/Whats-New-SharePoint-2010-Searching-External-Repositories-using-BCS",
    "VideoPageThumb": "https://sec.ch9.ms/ecn/ch9/5/5/5/6/5/5/WhatsNewSPS2010BCS_512_ch9.png",
    "ShowName": "jwiese",
    "VideoLength": "00:07:50",
    "VideoTitle": "What's New: SharePoint 2010 -- Searching External Repositories using BCS",
    "Author": "John Wiese",
    "UtcDateTimePublished": "2010-06-20T01:44:00Z",
    "ActualVideoFileLink": "https://sec.ch9.ms/ecn/ch9/5/5/5/6/5/5/WhatsNewSPS2010BCS_ch9.mp4",
    "Description": "What's New: SharePoint 2010 is a series of screencasts centered on what is new in SharePoint 2010 for developers. My goal is to highlight a majority of the major new features that are of interest to d"
  },
  {
    "VideoId": "d1a3f974-d7dd-48ab-95e6-9deb0007a9c6",
    "DataApi": "/Entries(guid'd1a3f974-d7dd-48ab-95e6-9deb0007a9c6')/",
    "VideoPageLink": "/Blogs/jwiese/Whats-New-SharePoint-2010-Customizing-the-Ribbon",
    "VideoPageThumb": "https://sec.ch9.ms/ecn/ch9/1/0/2/2/5/5/WhatsNewSharePoint2010Ribbon_512_ch9.png",
    "ShowName": "jwiese",
    "VideoLength": "00:12:09",
    "VideoTitle": "What's New: SharePoint 2010 -- Customizing the Ribbon",
    "Author": "John Wiese",
    "UtcDateTimePublished": "2010-05-26T13:05:00Z",
    "ActualVideoFileLink": "https://sec.ch9.ms/ecn/ch9/1/0/2/2/5/5/WhatsNewSharePoint2010Ribbon_ch9.mp4",
    "Description": "What's New: SharePoint 2010 is a series of screencasts centered on what is new in SharePoint 2010 for developers. My goal is to highlight a majority of the major new features that are of interest to d"
  },
  {
    "VideoId": "69284c4d-0685-429f-b4bd-9deb0007ad2f",
    "DataApi": "/Entries(guid'69284c4d-0685-429f-b4bd-9deb0007ad2f')/",
    "VideoPageLink": "/Blogs/jwiese/Whats-New-SharePoint-2010-Silverlight-and-the-Client-Object-Model",
    "VideoPageThumb": "https://sec.ch9.ms/ecn/ch9/8/6/3/9/4/5/WhatsNewSharePoint2010Silverlight_512_ch9.png",
    "ShowName": "jwiese",
    "VideoLength": "00:16:35",
    "VideoTitle": "What's New: SharePoint 2010 -- Silverlight and the Client Object Model",
    "Author": "John Wiese",
    "UtcDateTimePublished": "2010-05-11T23:58:00Z",
    "ActualVideoFileLink": "https://sec.ch9.ms/ecn/ch9/8/6/3/9/4/5/WhatsNewSharePoint2010Silverlight_ch9.mp4",
    "Description": "What's New: SharePoint 2010 is a series of screencasts centered on what is new in SharePoint 2010 for developers. My goal is to highlight a majority of the major new features that are of interest to d"
  },
  {
    "VideoId": "90b98197-34e1-47b5-8044-9deb0007b0c2",
    "DataApi": "/Entries(guid'90b98197-34e1-47b5-8044-9deb0007b0c2')/",
    "VideoPageLink": "/Blogs/jwiese/Whats-New-SharePoint-2010-Sandboxed-Solutions",
    "VideoPageThumb": "https://sec.ch9.ms/ecn/ch9/3/3/1/9/4/5/WhatsNewSP2010Sandbox_512_ch9.png",
    "ShowName": "jwiese",
    "VideoLength": "00:08:40",
    "VideoTitle": "What's New: SharePoint 2010 -- Sandboxed Solutions",
    "Author": "John Wiese",
    "UtcDateTimePublished": "2010-05-10T17:49:00Z",
    "ActualVideoFileLink": "https://sec.ch9.ms/ecn/ch9/3/3/1/9/4/5/WhatsNewSP2010Sandbox_ch9.mp4",
    "Description": "What's New: SharePoint 2010 is a series of screencasts centered on what is new in SharePoint 2010 for developers. My goal is to highlight a majority of the major new features that are of interest to d"
  },
  {
    "VideoId": "eeebb72e-6ef6-4e29-bacf-9deb0007b9f4",
    "DataApi": "/Entries(guid'eeebb72e-6ef6-4e29-bacf-9deb0007b9f4')/",
    "VideoPageLink": "/Blogs/jwiese/Whats-New-SharePoint-2010-Installing-on-Windows-7",
    "VideoPageThumb": "https://sec.ch9.ms/ecn/ch9/4/4/1/8/4/5/SP2010InstallWin7_512_ch9.png",
    "ShowName": "jwiese",
    "VideoLength": "00:11:55",
    "VideoTitle": "What's New: SharePoint 2010 - Installing on Windows 7",
    "Author": "John Wiese",
    "UtcDateTimePublished": "2010-05-04T20:24:00Z",
    "ActualVideoFileLink": "https://sec.ch9.ms/ecn/ch9/4/4/1/8/4/5/SP2010InstallWin7_ch9.mp4",
    "Description": "What's New: SharePoint 2010 is a series of screencasts centered on what is new in SharePoint 2010 for developers. My goal is to highlight a majority of the major new features that are of interest to d"
  },
  {
    "VideoId": "267844e7-1968-4a20-bdfc-9deb0008221f",
    "DataApi": "/Entries(guid'267844e7-1968-4a20-bdfc-9deb0008221f')/",
    "VideoPageLink": "/Blogs/jwiese/Using-WPF-in-Office-Add-Ins",
    "VideoPageThumb": "https://sec.ch9.ms/llnwd/ch9/8/0/3/6/7/4/WPFInOffice_large_ch9.png",
    "ShowName": "jwiese",
    "VideoLength": "00:09:13",
    "VideoTitle": "Using WPF in Office Add-Ins",
    "Author": "John Wiese",
    "UtcDateTimePublished": "2009-06-30T21:49:00Z",
    "ActualVideoFileLink": "https://sec.ch9.ms/llnwd/ch9/8/0/3/6/7/4/WPFInOffice_ch9.mp4",
    "Description": "\nWith WPF becoming more and more prevalent I thought it would be a good idea to revisit using WPF in office add-ins.   Way back when we launched Office 2007 one of the demo’s we did was an Outlook ad"
  },
  {
    "VideoId": "866edda2-a594-40fe-bf58-9deb000825a1",
    "DataApi": "/Entries(guid'866edda2-a594-40fe-bf58-9deb000825a1')/",
    "VideoPageLink": "/Blogs/jwiese/Publishing-a-Office-add-in-to-a-SharePoint-Site-for-Distribution",
    "VideoPageThumb": "https://sec.ch9.ms/llnwd/ch9/5/6/3/4/7/4/VSTO2SharePoint_large_ch9.png",
    "ShowName": "jwiese",
    "VideoLength": "00:05:32",
    "VideoTitle": "Publishing an Office add-in to a SharePoint Site for Distribution",
    "Author": "John Wiese",
    "UtcDateTimePublished": "2009-06-19T13:10:00Z",
    "ActualVideoFileLink": "https://sec.ch9.ms/llnwd/ch9/5/6/3/4/7/4/VSTO2SharePoint_ch9.mp4",
    "Description": "I've been asked many times, &quot;How do I publish my VSTO/Office Add-in installation files to a SharePoint site?&quot;.  It's relatively straight-forward to publish to a basic web site, or to a UNC f"
  },
  {
    "VideoId": "7ef6ff08-6ce5-41d3-9e3d-9deb00082930",
    "DataApi": "/Entries(guid'7ef6ff08-6ce5-41d3-9e3d-9deb00082930')/",
    "VideoPageLink": "/Blogs/jwiese/NET-4-VS-2010-and-Office-New-Features-in-VS-2010-for-Developers",
    "VideoPageThumb": "https://sec.ch9.ms/llnwd/ch9/8/3/7/0/7/4/OfficeVS10SC1_large_ch9.png",
    "ShowName": "jwiese",
    "VideoLength": "00:10:55",
    "VideoTitle": ".NET 4, VS 2010 and Office: New Features in VS 2010 for Developers",
    "Author": "John Wiese",
    "UtcDateTimePublished": "2009-05-28T13:00:00Z",
    "ActualVideoFileLink": "https://sec.ch9.ms/llnwd/ch9/8/3/7/0/7/4/OfficeVS10SC1_ch9.mp4",
    "Description": "Now that .NET 4 and VS 2010 are out, at least in Beta, I thought it would be a good time to show off some of the new features that are applicable to Office development.  In this second (see the first "
  },
  {
    "VideoId": "8eeeb239-cc48-4d71-8a88-9deb00082cba",
    "DataApi": "/Entries(guid'8eeeb239-cc48-4d71-8a88-9deb00082cba')/",
    "VideoPageLink": "/Blogs/jwiese/NET-4-VS-2010-and-Office-New-Features-in-NET-4-for-Office-Developers",
    "VideoPageThumb": "https://sec.ch9.ms/llnwd/ch9/3/7/7/3/4/4/net4OfficeSC1_large_ch9.png",
    "ShowName": "jwiese",
    "VideoLength": "00:13:19",
    "VideoTitle": ".NET 4, VS 2010 and Office:  New Features in .NET 4 for Office Developers",
    "Author": "John Wiese",
    "UtcDateTimePublished": "2009-05-27T15:18:00Z",
    "ActualVideoFileLink": "https://sec.ch9.ms/llnwd/ch9/3/7/7/3/4/4/net4OfficeSC1_ch9.mp4",
    "Description": "Now that .NET 4 and VS 2010 are out, at least in Beta, I thought it would be a good time to show off some of the new features that are applicable to Office development.  In this first screencast I wil"
  },
  {
    "VideoId": "d6967ca5-b56f-422a-bf04-9deb000830fd",
    "DataApi": "/Entries(guid'd6967ca5-b56f-422a-bf04-9deb000830fd')/",
    "VideoPageLink": "/Blogs/jwiese/Adding-Tabs-to-a-TabSet-in-Office-2007-Apps",
    "VideoPageThumb": null,
    "ShowName": null,
    "VideoLength": "00:00:00",
    "VideoTitle": null,
    "Author": null,
    "UtcDateTimePublished": "0001-01-01T00:00:00",
    "ActualVideoFileLink": null,
    "Description": null
  },
  {
    "VideoId": "e253dd13-81fe-410f-85b0-9deb000834db",
    "DataApi": "/Entries(guid'e253dd13-81fe-410f-85b0-9deb000834db')/",
    "VideoPageLink": "/Blogs/jwiese/How-to-Send-Just-a-few-Slides-from-PowerPoint-as-an-Email-Attachment",
    "VideoPageThumb": null,
    "ShowName": null,
    "VideoLength": "00:00:00",
    "VideoTitle": null,
    "Author": null,
    "UtcDateTimePublished": "0001-01-01T00:00:00",
    "ActualVideoFileLink": null,
    "Description": null
  }
]