[
  {
    "VideoId": "8c2e8c04-7eb8-44e7-ba25-9deb000df258",
    "DataApi": "/Entries(guid'8c2e8c04-7eb8-44e7-ba25-9deb000df258')/",
    "VideoPageLink": "/Blogs/Learn/Office-2010-and-SharePoint-2010-Training-Courses-Updated",
    "VideoPageThumb": null,
    "ShowName": null,
    "VideoLength": "00:00:00",
    "VideoTitle": null,
    "Author": null,
    "UtcDateTimePublished": "0001-01-01T00:00:00",
    "ActualVideoFileLink": null,
    "Description": null
  },
  {
    "VideoId": "4e53de42-3b8b-4695-8d6b-9deb002fc51e",
    "DataApi": "/Entries(guid'4e53de42-3b8b-4695-8d6b-9deb002fc51e')/",
    "VideoPageLink": "/Blogs/Learn/Silverlight-Training",
    "VideoPageThumb": null,
    "ShowName": null,
    "VideoLength": "00:00:00",
    "VideoTitle": null,
    "Author": null,
    "UtcDateTimePublished": "0001-01-01T00:00:00",
    "ActualVideoFileLink": null,
    "Description": null
  },
  {
    "VideoId": "249b24d8-b8cf-472b-add6-9deb002fc1c4",
    "DataApi": "/Entries(guid'249b24d8-b8cf-472b-add6-9deb002fc1c4')/",
    "VideoPageLink": "/Blogs/Learn/Windows-Phone-7-Series-Training",
    "VideoPageThumb": null,
    "ShowName": null,
    "VideoLength": "00:00:00",
    "VideoTitle": null,
    "Author": null,
    "UtcDateTimePublished": "0001-01-01T00:00:00",
    "ActualVideoFileLink": null,
    "Description": null
  },
  {
    "VideoId": "3135d0d8-6581-4584-93b4-9deb002fca0e",
    "DataApi": "/Entries(guid'3135d0d8-6581-4584-93b4-9deb002fca0e')/",
    "VideoPageLink": "/Blogs/Learn/Using-Access-2010-and-SharePoint-2010-Services",
    "VideoPageThumb": null,
    "ShowName": null,
    "VideoLength": "00:00:00",
    "VideoTitle": null,
    "Author": null,
    "UtcDateTimePublished": "0001-01-01T00:00:00",
    "ActualVideoFileLink": null,
    "Description": null
  },
  {
    "VideoId": "093bde7c-1aad-4226-b216-9deb002fd511",
    "DataApi": "/Entries(guid'093bde7c-1aad-4226-b216-9deb002fd511')/",
    "VideoPageLink": "/Blogs/Learn/SharePoint-2010-Training-Kit-Update",
    "VideoPageThumb": null,
    "ShowName": null,
    "VideoLength": "00:00:00",
    "VideoTitle": null,
    "Author": null,
    "UtcDateTimePublished": "0001-01-01T00:00:00",
    "ActualVideoFileLink": null,
    "Description": null
  },
  {
    "VideoId": "7b706a16-b928-4895-ad79-9deb002fd760",
    "DataApi": "/Entries(guid'7b706a16-b928-4895-ad79-9deb002fd760')/",
    "VideoPageLink": "/Blogs/Learn/Silverlight-4-Training-Course-Available",
    "VideoPageThumb": null,
    "ShowName": null,
    "VideoLength": "00:00:00",
    "VideoTitle": null,
    "Author": null,
    "UtcDateTimePublished": "0001-01-01T00:00:00",
    "ActualVideoFileLink": null,
    "Description": null
  },
  {
    "VideoId": "e97471ef-e4c6-471c-bcee-9deb002fdccb",
    "DataApi": "/Entries(guid'e97471ef-e4c6-471c-bcee-9deb002fdccb')/",
    "VideoPageLink": "/Blogs/Learn/Azure-High-Performance-Computing-and-Identity-Training-Courses",
    "VideoPageThumb": null,
    "ShowName": null,
    "VideoLength": "00:00:00",
    "VideoTitle": null,
    "Author": null,
    "UtcDateTimePublished": "0001-01-01T00:00:00",
    "ActualVideoFileLink": null,
    "Description": null
  },
  {
    "VideoId": "adc9f5c0-fb57-4abd-970a-9deb002fdf1f",
    "DataApi": "/Entries(guid'adc9f5c0-fb57-4abd-970a-9deb002fdf1f')/",
    "VideoPageLink": "/Blogs/Learn/New-Office-2010-SharePoint-2010-and-Windows-Server-2008-R2-Courses",
    "VideoPageThumb": null,
    "ShowName": null,
    "VideoLength": "00:00:00",
    "VideoTitle": null,
    "Author": null,
    "UtcDateTimePublished": "0001-01-01T00:00:00",
    "ActualVideoFileLink": null,
    "Description": null
  },
  {
    "VideoId": "9417994c-c627-4c81-88d0-9deb002fe832",
    "DataApi": "/Entries(guid'9417994c-c627-4c81-88d0-9deb002fe832')/",
    "VideoPageLink": "/Blogs/Learn/Welcome-to-the-Channel-9-Learning-Center",
    "VideoPageThumb": null,
    "ShowName": null,
    "VideoLength": "00:00:00",
    "VideoTitle": null,
    "Author": null,
    "UtcDateTimePublished": "0001-01-01T00:00:00",
    "ActualVideoFileLink": null,
    "Description": null
  }
]